{"file:///d%3A/01%20School/1st%20Year%20College/1st%20term/CS%20101/Module%203/Pythagorean%20Calculator/PC4.2.cpp":{"language":"C++","code":284,"comment":36,"blank":70},"file:///d%3A/01%20School/1st%20Year%20College/1st%20term/CS%20101/Module%203/Pythagorean%20Calculator/Version%201%20-%203.3%20source%20codes/PC3.3.cpp":{"language":"C++","code":117,"comment":15,"blank":35},"file:///d%3A/01%20School/1st%20Year%20College/1st%20term/CS%20101/Module%203/Pythagorean%20Calculator/Version%203.4%20-%204.1%20source%20codes%20%26%20exe/PC3.5.cpp":{"language":"C++","code":130,"comment":17,"blank":38},"file:///d%3A/01%20School/1st%20Year%20College/1st%20term/CS%20101/Module%203/Pythagorean%20Calculator/Version%203.4%20-%204.1%20source%20codes%20%26%20exe/PC4.0.cpp":{"language":"C++","code":252,"comment":33,"blank":64},"file:///d%3A/01%20School/1st%20Year%20College/1st%20term/CS%20101/Module%203/Pythagorean%20Calculator/Version%201%20-%203.3%20source%20codes/PC3.2.cpp":{"language":"C++","code":113,"comment":14,"blank":35},"file:///d%3A/01%20School/1st%20Year%20College/1st%20term/CS%20101/Module%203/Pythagorean%20Calculator/Version%203.4%20-%204.1%20source%20codes%20%26%20exe/PC3.4.cpp":{"language":"C++","code":126,"comment":17,"blank":37},"file:///d%3A/01%20School/1st%20Year%20College/1st%20term/CS%20101/Module%203/Pythagorean%20Calculator/Version%201%20-%203.3%20source%20codes/PC3.0.cpp":{"language":"C++","code":87,"comment":10,"blank":36},"file:///d%3A/01%20School/1st%20Year%20College/1st%20term/CS%20101/Module%203/Pythagorean%20Calculator/Version%201%20-%203.3%20source%20codes/PC2.0.cpp":{"language":"C++","code":61,"comment":5,"blank":27},"file:///d%3A/01%20School/1st%20Year%20College/1st%20term/CS%20101/Module%203/Pythagorean%20Calculator/Version%201%20-%203.3%20source%20codes/PC3.1.cpp":{"language":"C++","code":94,"comment":7,"blank":37},"file:///d%3A/01%20School/1st%20Year%20College/1st%20term/CS%20101/Module%203/Pythagorean%20Calculator/Version%201%20-%203.3%20source%20codes/PC1.0.cpp":{"language":"C++","code":48,"comment":4,"blank":24},"file:///d%3A/01%20School/1st%20Year%20College/1st%20term/CS%20101/Module%203/Pythagorean%20Calculator/Version%203.4%20-%204.1%20source%20codes%20%26%20exe/PC4.1.cpp":{"language":"C++","code":269,"comment":34,"blank":67}}